db_fg/__init__.py
db_fg/db_fg.py
db_fg-0.0.3.dist-info/METADATA
db_fg-0.0.3.dist-info/WHEEL
db_fg-0.0.3.dist-info/top_level.txt
db_fg-0.0.3.dist-info/RECORD
